LAB 9/Ques1/Q2/Q2.v
module Q2(input cin,input x,input y,output s,output cout);
    assign s = x ^ y ^ cin;
    assign cout = (x & y) | (x & cin) | (y & cin);
endmodule

LAB 9/Ques1/Q2/Q2_tb.v
`timescale 1ns/1ns
`include "Q2.v"

module Q2_tb();
reg x,y,cin;
wire cout,s;
Q2 Q_2(cin,x,y,s,cout);
initial begin
    $dumpfile("Q2_tb.vcd");
    $dumpvars(0,Q2_tb);
    x = 0; y = 0; cin = 0; #20;    
    x = 0; y = 0; cin = 1; #20;
    x = 0; y = 1; cin = 0; #20;
    x = 0; y = 1; cin = 1; #20;
    x = 1; y = 0; cin = 0; #20;
    x = 1; y = 0; cin = 1; #20;
    x = 1; y = 1; cin = 0; #20;
    x = 1; y = 1; cin = 1; #20;

    $display("Test Completed");
end
endmodule

LAB 9/Ques1/Q2/Q2_tb.vcd
$date
	Sat Nov  5 14:32:25 2022
$end
$version
	Icarus Verilog
$end
$timescale
	1ns
$end
$scope module Q2_tb $end
$var wire 1 ! s $end
$var wire 1 " cout $end
$var reg 1 # cin $end
$var reg 1 $ x $end
$var reg 1 % y $end
$scope module Q_2 $end
$var wire 1 # cin $end
$var wire 1 " cout $end
$var wire 1 ! s $end
$var wire 1 $ x $end
$var wire 1 % y $end
$upscope $end
$upscope $end
$enddefinitions $end
#0
$dumpvars
0%
0$
0#
0"
0!
$end
#20
1!
1#
#40
0#
1%
#60
1"
0!
1#
#80
0"
1!
0#
0%
1$
#100
1"
0!
1#
#120
0#
1%
#140
1!
1#
