LAB 9/Ques1/Q3/Q3.v
module halfadd(input x,input y,output s,output c);

    assign s = x ^ y;
    assign c = x & y;
endmodule

module Q3(input x,input y,input z,output s,output c);

    wire ha1_s,ha1_c,ha2_s,ha2_c,out_s,out_c;

    halfadd h1(x,y,ha1_s,ha1_c);
    halfadd h2(z,ha1_s,ha2_s,ha2_c);

    assign s = ha2_s;
    assign c = ha1_c | ha2_c;

endmodule

LAB 9/Ques1/Q3/Q3_tb.v
`timescale 1ns/1ns
`include "Q3.v"

module Q3_tb();

reg x,y,z;
wire s,c;

Q3 Q_3(x,y,z,s,c);
initial begin
    $dumpfile("Q3_tb.vcd");
    $dumpvars(0,Q3_tb);
    x = 0; y = 0; z = 0; #20;
    x = 0; y = 0; z = 1; #20;
    x = 0; y = 1; z = 0; #20;
    x = 0; y = 1; z = 1; #20;
    x = 1; y = 0; z = 0; #20;
    x = 1; y = 0; z = 1; #20;
    x = 1; y = 1; z = 0; #20;
    x = 1; y = 1; z = 1; #20;
    $display("Test Completed");
end
endmodule

LAB 9/Ques1/Q3/Q3_tb.vcd
$date
	Sat Nov  5 14:46:47 2022
$end
$version
	Icarus Verilog
$end
$timescale
	1ns
$end
$scope module Q3_tb $end
$var wire 1 ! s $end
$var wire 1 " c $end
$var reg 1 # x $end
$var reg 1 $ y $end
$var reg 1 % z $end
$scope module Q_3 $end
$var wire 1 " c $end
$var wire 1 ! s $end
$var wire 1 # x $end
$var wire 1 $ y $end
$var wire 1 % z $end
$var wire 1 & ha2_s $end
$var wire 1 ' ha2_c $end
$var wire 1 ( ha1_s $end
$var wire 1 ) ha1_c $end
$scope module h1 $end
$var wire 1 ) c $end
$var wire 1 ( s $end
$var wire 1 # x $end
$var wire 1 $ y $end
$upscope $end
$scope module h2 $end
$var wire 1 ' c $end
$var wire 1 & s $end
$var wire 1 % x $end
$var wire 1 ( y $end
$upscope $end
$upscope $end
$upscope $end
$enddefinitions $end
#0
$dumpvars
0)
0(
0'
0&
0%
0$
0#
0"
0!
$end
#20
1!
1&
1%
#40
1(
0%
1$
#60
1"
0!
0&
1'
1%
#80
0"
1!
1&
0'
0%
0$
1#
#100
1"
0!
0&
1'
1%
#120
0'
0(
1)
0%
1$
#140
1!
1&
1%
